rcluster/__exec__.py
rcluster/__init__.py
rcluster/pmkutils.py
rcluster/rcluster.py
rcluster/data/ami.sh
rcluster/data/config.json
rcluster-0.2.27.dist-info/DESCRIPTION.rst
rcluster-0.2.27.dist-info/METADATA
rcluster-0.2.27.dist-info/RECORD
rcluster-0.2.27.dist-info/WHEEL
rcluster-0.2.27.dist-info/entry_points.txt
rcluster-0.2.27.dist-info/metadata.json
rcluster-0.2.27.dist-info/top_level.txt
