Metadata-Version: 2.0
Name: rcluster
Version: 0.2.27
Summary: R clusters on AWS
Home-page: https://github.com/ElizabethAB/rcluster
Author: Elizabeth Byerly
Author-email: elizabeth.byerly@gmail.com
License: MIT
Keywords: r aws cluster cloud
Platform: UNKNOWN
Classifier: Development Status :: 4 - Beta
Classifier: License :: OSI Approved :: MIT License
Classifier: Programming Language :: Python :: 3
Classifier: Operating System :: OS Independent
Classifier: Intended Audience :: End Users/Desktop
Classifier: Intended Audience :: System Administrators
Classifier: Topic :: System :: Clustering
Classifier: Topic :: Scientific/Engineering
Classifier: Topic :: System :: Systems Administration
Requires-Dist: boto3
Requires-Dist: paramiko
Provides-Extra: dev
Requires-Dist: coverage; extra == 'dev'
Requires-Dist: pypandoc; extra == 'dev'
Requires-Dist: pytest; extra == 'dev'
